ChelsiAI/CONSTANT.py
ChelsiAI/__init__.py
ChelsiAI/features_default.py
ChelsiAI/features/__init__.py
ChelsiAI/features/chatbot/__init__.py
ChelsiAI/features/chatbot/chatbot.py
ChelsiAI/features/chatbot/goodbye.py
ChelsiAI/features/chatbot/greet.py
ChelsiAI/features/chatbot/click_photo/__init__.py
ChelsiAI/features/chatbot/click_photo/click_photo.py
ChelsiAI/features/chatbot/covid_cases/__init__.py
ChelsiAI/features/chatbot/covid_cases/covid_cases.py
ChelsiAI/features/chatbot/date_time/__init__.py
ChelsiAI/features/chatbot/date_time/date_time.py
ChelsiAI/features/chatbot/games/__init__.py
ChelsiAI/features/chatbot/games/games.py
ChelsiAI/features/chatbot/iambored/__init__.py
ChelsiAI/features/chatbot/iambored/iambored.py
ChelsiAI/features/chatbot/internet_speed_test/__init__.py
ChelsiAI/features/chatbot/internet_speed_test/internet_speed_test.py
ChelsiAI/features/chatbot/joke/__init__.py
ChelsiAI/features/chatbot/joke/joke.py
ChelsiAI/features/chatbot/news/__init__.py
ChelsiAI/features/chatbot/news/news.py
ChelsiAI/features/chatbot/places_near_me/__init__.py
ChelsiAI/features/chatbot/places_near_me/places_near_me.py
ChelsiAI/features/chatbot/screenshot/__init__.py
ChelsiAI/features/chatbot/screenshot/screenshot.py
ChelsiAI/features/chatbot/send_email/__init__.py
ChelsiAI/features/chatbot/send_email/send_email.py
ChelsiAI/features/chatbot/tell_me_about/__init__.py
ChelsiAI/features/chatbot/tell_me_about/tell_me_about.py
ChelsiAI/features/chatbot/volume_control/__init__.py
ChelsiAI/features/chatbot/volume_control/volume_controller.py
ChelsiAI/features/chatbot/weather/__init__.py
ChelsiAI/features/chatbot/weather/weather.py
ChelsiAI/features/chatbot/website_open/__init__.py
ChelsiAI/features/chatbot/website_open/website_open.py
ChelsiAI/features/chatbot/whatsapp_message/__init__.py
ChelsiAI/features/chatbot/whatsapp_message/whatsapp_message.py
ChelsiAI/features/chatbot/youtube_play/__init__.py
ChelsiAI/features/chatbot/youtube_play/youtube_play.py
ChelsiAI-2.9.dist-info/METADATA
ChelsiAI-2.9.dist-info/WHEEL
ChelsiAI-2.9.dist-info/top_level.txt
ChelsiAI-2.9.dist-info/RECORD
