Metadata-Version: 2.1
Name: ChelsiAI
Version: 2.9
Summary: ChelsiAI is python library to build your own AI virtual assistant with natural language processing.
Home-page: https://yashkumarvaibhav.github.io/mysite
Author: Yash Kumar Vaibhav & Team
Author-email: chelsiai2022@gmail.com
License: UNKNOWN
Project-URL: Documentation, https://github.com/
Project-URL: Donate, https://www.buymeacoffee.com/
Project-URL: Say Thanks!, https://youtube.com/@yashvaibhav9546
Project-URL: Source, https://github.com/
Platform: UNKNOWN
Classifier: Programming Language :: Python :: 3
Classifier: License :: OSI Approved :: MIT License
Classifier: Operating System :: OS Independent
Requires-Python: >=3.6
Requires-Dist: numpy
Requires-Dist: gtts
Requires-Dist: playsound
Requires-Dist: pyscreenshot
Requires-Dist: opencv-python
Requires-Dist: SpeechRecognition
Requires-Dist: pipwin
Requires-Dist: lxml
Requires-Dist: pyjokes
Requires-Dist: beautifulsoup4
Requires-Dist: wikipedia
Requires-Dist: scipy
Requires-Dist: download
Requires-Dist: torch
Requires-Dist: lazyme
Requires-Dist: requests
Requires-Dist: pyttsx3
Requires-Dist: googlesearch-python
Requires-Dist: spacy
Requires-Dist: textdistance
Requires-Dist: pywhatkit
Requires-Dist: youtube-search-python
Requires-Dist: shutup
Requires-Dist: Flask
Requires-Dist: speedtest-cli
Requires-Dist: pytube
Requires-Dist: pycountry
Requires-Dist: phonetics
Requires-Dist: fuzzywuzzy
Requires-Dist: googletrans
Requires-Dist: wave
Requires-Dist: deepspeech
Requires-Dist: halo
Requires-Dist: playsound (==1.2.2)
Requires-Dist: pyaudio
Requires-Dist: mediapipe (==0.8.11)
Requires-Dist: pycaw
